{"cameraMode":{"drawMode":0,"name":"Shaded","section":"Shading Mode"},"sceneLighting":true,"audioPlay":false,"sceneViewState":{"m_AlwaysRefresh":false,"showFog":true,"showSkybox":true,"showFlares":true,"showImageEffects":true,"showParticleSystems":true,"showVisualEffectGraphs":true,"m_FxEnabled":true},"in2DMode":false,"pivot":{"x":9.63296127319336,"y":7.786639213562012,"z":16.667837142944337},"rotation":{"x":0.0609196275472641,"y":0.6138796806335449,"z":0.04760511964559555,"w":-0.7856134176254273},"size":1.8503104448318482,"orthographic":false}